chaya/__init__.py
chaya/hookspecs.py
chaya/plugin.py
chaya/core/__init__.py
chaya/core/config.py
chaya/core/manager.py
chaya/core/model.py
chaya/core/query.py
chaya/core/records.py
chaya/core/storage.py
chaya/core/ui.py
chaya/plugins/__init__.py
chaya/plugins/records/__init__.py
chaya/plugins/records/article/__init__.py
chaya/plugins/records/book/__init__.py
chaya/plugins/records/paper/__init__.py
chaya/plugins/records/webpage/__init__.py
chaya/plugins/storage/__init__.py
chaya/plugins/storage/sql/__init__.py
chaya/plugins/storage/yaml/__init__.py
chaya/plugins/ui/__init__.py
chaya/plugins/ui/tui/__init__.py
chaya/utils/__init__.py
chaya/utils/cli.py
chaya-2024.4.0.dist-info/METADATA
chaya-2024.4.0.dist-info/WHEEL
chaya-2024.4.0.dist-info/entry_points.txt
chaya-2024.4.0.dist-info/licenses/LICENSE
chaya-2024.4.0.dist-info/RECORD
