Metadata-Version: 2.4
Name: chaya
Version: 2024.4.0
Summary: CLI-first, plugin-extensible personal library manager
Author-email: Bertold Sedlak <bertold.sedlak@gmail.com>
License-Expression: MIT
License-File: LICENSE
Requires-Python: >=3.11
Requires-Dist: click>=8.1.8
Requires-Dist: pluggy>=1.5.0
Requires-Dist: pyaml>=25.1.0
Requires-Dist: pydantic>=2.11.4
Requires-Dist: rich>=14.0.0
Requires-Dist: tomli-w>=1.2.0
Requires-Dist: tomli>=2.2.1
